{
  "status": "ok",
  "data": {
    "aqi": 56,
    "idx": 243,
    "attributions": [
      {
        "url": "http://www.airnow.gov/",
        "name": "Air Now - US EPA"
      },
      {
        "url": "http://www.arb.ca.gov/",
        "name": "CARB - California Air Resources Board",
        "logo": "USA-CAARB.png"
      },
      {
        "url": "http://www.aqmd.gov/",
        "name": "South Coast Air Quality Management District (AQMD)",
        "logo": "USA-SouthCoastAQMD.png"
      },
      {
        "url": "https://waqi.info/",
        "name": "World Air Quality Index Project"
      }
    ],
    "city": {
      "geo": [
        34.06653,
        -118.22676
      ],
      "name": "Los Angeles-North Main Street",
      "url": "https://aqicn.org/city/losangeles/los-angeles-north-main-street",
      "location": ""
    },
    "dominentpol": "o3",
    "iaqi": {
      "co": {
        "v": 3.4
      },
      "h": {
        "v": 45.6
      },
      "no2": {
        "v": 9
      },
      "o3": {
        "v": 55.8
      },
      "p": {
        "v": 1038.3
      },
      "pm10": {
        "v": 23
      },
      "pm25": {
        "v": 50
      },
      "so2": {
        "v": 0.8
      },
      "t": {
        "v": 22.9
      },
      "w": {
        "v": 0.3
      },
      "wg": {
        "v": 1
      }
    },
    "time": {
      "s": "2025-04-09 17:00:00",
      "tz": "-07:00",
      "v": 1744218000,
      "iso": "2025-04-09T17:00:00-07:00"
    },
    "forecast": {
      "daily": {
        "uvi": [
          {
            "avg": 1,
            "day": "2025-04-07",
            "max": 8,
            "min": 0
          },
          {
            "avg": 1,
            "day": "2025-04-08",
            "max": 9,
            "min": 0
          },
          {
            "avg": 1,
            "day": "2025-04-09",
            "max": 9,
            "min": 0
          },
          {
            "avg": 1,
            "day": "2025-04-10",
            "max": 9,
            "min": 0
          },
          {
            "avg": 1,
            "day": "2025-04-11",
            "max": 9,
            "min": 0
          },
          {
            "avg": 1,
            "day": "2025-04-12",
            "max": 9,
            "min": 0
          },
          {
            "avg": 1,
            "day": "2025-04-13",
            "max": 8,
            "min": 0
          },
          {
            "avg": 0,
            "day": "2025-04-14",
            "max": 0,
            "min": 0
          }
        ]
      }
    },
    "debug": {
      "sync": "2025-04-10T10:17:17+09:00"
    }
  }
}
