{
  "status": "ok",
  "data": {
    "aqi": 36,
    "idx": 243,
    "attributions": [
      {
        "url": "http://www.airnow.gov/",
        "name": "Air Now - US EPA"
      },
      {
        "url": "http://www.arb.ca.gov/",
        "name": "CARB - California Air Resources Board",
        "logo": "USA-CAARB.png"
      },
      {
        "url": "http://www.aqmd.gov/",
        "name": "South Coast Air Quality Management District (AQMD)",
        "logo": "USA-SouthCoastAQMD.png"
      },
      {
        "url": "https://waqi.info/",
        "name": "World Air Quality Index Project"
      }
    ],
    "city": {
      "geo": [
        34.06653,
        -118.22676
      ],
      "name": "Los Angeles-North Main Street",
      "url": "https://aqicn.org/city/losangeles/los-angeles-north-main-street",
      "location": ""
    },
    "dominentpol": "o3",
    "iaqi": {
      "co": {
        "v": 2.3
      },
      "h": {
        "v": 74.4
      },
      "no2": {
        "v": 3
      },
      "o3": {
        "v": 36.1
      },
      "p": {
        "v": 1039.2
      },
      "pm10": {
        "v": 9
      },
      "pm25": {
        "v": 18
      },
      "so2": {
        "v": 0.2
      },
      "t": {
        "v": 11.6
      },
      "w": {
        "v": 0.4
      },
      "wg": {
        "v": 1.2
      }
    },
    "time": {
      "s": "2023-03-05 17:00:00",
      "tz": "-08:00",
      "v": 1678035600,
      "iso": "2023-03-05T17:00:00-08:00"
    },
    "forecast": {
      "daily": {
        "o3": [
          {
            "avg": 5,
            "day": "2023-03-03",
            "max": 35,
            "min": 1
          },
          {
            "avg": 8,
            "day": "2023-03-04",
            "max": 18,
            "min": 1
          },
          {
            "avg": 9,
            "day": "2023-03-05",
            "max": 17,
            "min": 8
          },
          {
            "avg": 5,
            "day": "2023-03-06",
            "max": 16,
            "min": 1
          },
          {
            "avg": 5,
            "day": "2023-03-07",
            "max": 28,
            "min": 1
          },
          {
            "avg": 5,
            "day": "2023-03-08",
            "max": 30,
            "min": 1
          },
          {
            "avg": 7,
            "day": "2023-03-09",
            "max": 58,
            "min": 1
          },
          {
            "avg": 9,
            "day": "2023-03-10",
            "max": 14,
            "min": 3
          }
        ],
        "pm10": [
          {
            "avg": 76,
            "day": "2023-03-03",
            "max": 98,
            "min": 47
          },
          {
            "avg": 38,
            "day": "2023-03-04",
            "max": 93,
            "min": 7
          },
          {
            "avg": 18,
            "day": "2023-03-05",
            "max": 26,
            "min": 5
          },
          {
            "avg": 28,
            "day": "2023-03-06",
            "max": 53,
            "min": 5
          },
          {
            "avg": 37,
            "day": "2023-03-07",
            "max": 56,
            "min": 17
          },
          {
            "avg": 61,
            "day": "2023-03-08",
            "max": 83,
            "min": 29
          },
          {
            "avg": 103,
            "day": "2023-03-09",
            "max": 151,
            "min": 61
          },
          {
            "avg": 120,
            "day": "2023-03-10",
            "max": 157,
            "min": 72
          }
        ],
        "pm25": [
          {
            "avg": 163,
            "day": "2023-03-03",
            "max": 183,
            "min": 124
          },
          {
            "avg": 92,
            "day": "2023-03-04",
            "max": 180,
            "min": 16
          },
          {
            "avg": 49,
            "day": "2023-03-05",
            "max": 71,
            "min": 13
          },
          {
            "avg": 66,
            "day": "2023-03-06",
            "max": 117,
            "min": 12
          },
          {
            "avg": 85,
            "day": "2023-03-07",
            "max": 127,
            "min": 54
          },
          {
            "avg": 143,
            "day": "2023-03-08",
            "max": 171,
            "min": 79
          },
          {
            "avg": 202,
            "day": "2023-03-09",
            "max": 278,
            "min": 152
          },
          {
            "avg": 230,
            "day": "2023-03-10",
            "max": 297,
            "min": 169
          }
        ]
      }
    },
    "debug": {
      "sync": "2023-03-06T10:24:39+09:00"
    }
  }
}
