{
  "status": "ok",
  "data": {
    "aqi": 55,
    "idx": 243,
    "attributions": [
      {
        "url": "http://www.aqmd.gov/",
        "name": "South Coast Air Quality Management District (AQMD)",
        "logo": "USA-SouthCoastAQMD.png"
      },
      {
        "url": "http://www.airnow.gov/",
        "name": "Air Now - US EPA"
      },
      {
        "url": "http://www.arb.ca.gov/",
        "name": "CARB - California Air Resources Board",
        "logo": "USA-CAARB.png"
      },
      {
        "url": "https://waqi.info/",
        "name": "World Air Quality Index Project"
      }
    ],
    "city": {
      "geo": [
        34.06653,
        -118.22676
      ],
      "name": "Los Angeles-North Main Street",
      "url": "https://aqicn.org/city/losangeles/los-angeles-north-main-street",
      "location": ""
    },
    "dominentpol": "pm25",
    "iaqi": {
      "co": {
        "v": 12.3
      },
      "h": {
        "v": 38.3
      },
      "no2": {
        "v": 40.2
      },
      "o3": {
        "v": 3.2
      },
      "p": {
        "v": 1038.4
      },
      "pm10": {
        "v": 51
      },
      "pm25": {
        "v": 55
      },
      "so2": {
        "v": 0.6
      },
      "t": {
        "v": 22.9
      },
      "w": {
        "v": 0.4
      },
      "wg": {
        "v": 0.1
      }
    },
    "time": {
      "s": "2024-10-23 08:00:00",
      "tz": "-07:00",
      "v": 1729670400,
      "iso": "2024-10-23T08:00:00-07:00"
    },
    "forecast": {
      "daily": {
        "o3": [
          {
            "avg": 6,
            "day": "2024-10-21",
            "max": 43,
            "min": 1
          },
          {
            "avg": 5,
            "day": "2024-10-22",
            "max": 51,
            "min": 1
          },
          {
            "avg": 16,
            "day": "2024-10-23",
            "max": 89,
            "min": 1
          },
          {
            "avg": 10,
            "day": "2024-10-24",
            "max": 64,
            "min": 1
          },
          {
            "avg": 7,
            "day": "2024-10-25",
            "max": 71,
            "min": 1
          },
          {
            "avg": 6,
            "day": "2024-10-26",
            "max": 58,
            "min": 1
          },
          {
            "avg": 8,
            "day": "2024-10-27",
            "max": 37,
            "min": 4
          }
        ],
        "pm10": [
          {
            "avg": 35,
            "day": "2024-10-21",
            "max": 55,
            "min": 14
          },
          {
            "avg": 39,
            "day": "2024-10-22",
            "max": 66,
            "min": 25
          },
          {
            "avg": 82,
            "day": "2024-10-23",
            "max": 119,
            "min": 54
          },
          {
            "avg": 80,
            "day": "2024-10-24",
            "max": 124,
            "min": 51
          },
          {
            "avg": 73,
            "day": "2024-10-25",
            "max": 93,
            "min": 61
          },
          {
            "avg": 68,
            "day": "2024-10-26",
            "max": 83,
            "min": 52
          },
          {
            "avg": 60,
            "day": "2024-10-27",
            "max": 66,
            "min": 53
          }
        ],
        "pm25": [
          {
            "avg": 82,
            "day": "2024-10-21",
            "max": 132,
            "min": 44
          },
          {
            "avg": 88,
            "day": "2024-10-22",
            "max": 162,
            "min": 69
          },
          {
            "avg": 173,
            "day": "2024-10-23",
            "max": 220,
            "min": 124
          },
          {
            "avg": 171,
            "day": "2024-10-24",
            "max": 231,
            "min": 125
          },
          {
            "avg": 165,
            "day": "2024-10-25",
            "max": 187,
            "min": 155
          },
          {
            "avg": 160,
            "day": "2024-10-26",
            "max": 175,
            "min": 141
          },
          {
            "avg": 152,
            "day": "2024-10-27",
            "max": 159,
            "min": 135
          }
        ],
        "uvi": [
          {
            "avg": 1,
            "day": "2024-10-21",
            "max": 5,
            "min": 0
          },
          {
            "avg": 1,
            "day": "2024-10-22",
            "max": 6,
            "min": 0
          },
          {
            "avg": 1,
            "day": "2024-10-23",
            "max": 5,
            "min": 0
          },
          {
            "avg": 1,
            "day": "2024-10-24",
            "max": 6,
            "min": 0
          },
          {
            "avg": 1,
            "day": "2024-10-25",
            "max": 6,
            "min": 0
          },
          {
            "avg": 1,
            "day": "2024-10-26",
            "max": 5,
            "min": 0
          },
          {
            "avg": 2,
            "day": "2024-10-27",
            "max": 4,
            "min": 0
          }
        ]
      }
    },
    "debug": {
      "sync": "2024-10-24T02:01:51+09:00"
    }
  }
}
